pengyangca/__init__.py
pengyangca/py2/__init__.py
pengyangca/py2/py3.py
pengyangca/py2/py3b.py
pengyangca2-0.0.4.dist-info/LICENCE.txt
pengyangca2-0.0.4.dist-info/METADATA
pengyangca2-0.0.4.dist-info/WHEEL
pengyangca2-0.0.4.dist-info/top_level.txt
pengyangca2-0.0.4.dist-info/RECORD
