Metadata-Version: 2.1
Name: pengyangca2
Version: 0.0.4
Summary: A very basic calculator
Home-page: 
Author: Peng Kiina
Author-email: pyseptimo@outlook.com
License: MIT
Keywords: calculator
Classifier: Development Status :: 5 - Production/Stable
Classifier: Intended Audience :: Education
Classifier: Operating System :: Microsoft :: Windows :: Windows 10
Classifier: License :: OSI Approved :: MIT License
Classifier: Programming Language :: Python :: 3
License-File: LICENCE.txt
Requires-Dist: networkx
Requires-Dist: pyvis
Requires-Dist: leidenalg
Requires-Dist: autocorrect
Requires-Dist: coreferee
Requires-Dist: spacy (<3.5.0,>=3.0.0)
Requires-Dist: xlsxwriter
